sasstastic/__init__.py
sasstastic/__main__.py
sasstastic/cli.py
sasstastic/common.py
sasstastic/compile.py
sasstastic/config.py
sasstastic/download.py
sasstastic/logs.py
sasstastic/main.py
sasstastic/version.py
sasstastic-0.0.2.dist-info/LICENSE
sasstastic-0.0.2.dist-info/METADATA
sasstastic-0.0.2.dist-info/WHEEL
sasstastic-0.0.2.dist-info/entry_points.txt
sasstastic-0.0.2.dist-info/top_level.txt
sasstastic-0.0.2.dist-info/zip-safe
sasstastic-0.0.2.dist-info/RECORD
