Metadata-Version: 2.1
Name: sasstastic
Version: 0.0.2
Summary: Fantastic SASS and SCSS compilation for python
Home-page: https://github.com/samuelcolvin/sasstastic
Author: Samuel Colvin
Author-email: s@muelcolvin.com
License: MIT
Platform: UNKNOWN
Classifier: Development Status :: 4 - Beta
Classifier: Programming Language :: Python
Classifier: Programming Language :: Python :: 3
Classifier: Programming Language :: Python :: 3 :: Only
Classifier: Programming Language :: Python :: 3.7
Classifier: Programming Language :: Python :: 3.8
Classifier: Intended Audience :: Developers
Classifier: Intended Audience :: Information Technology
Classifier: Intended Audience :: System Administrators
Classifier: License :: OSI Approved :: MIT License
Classifier: Operating System :: Unix
Classifier: Operating System :: POSIX :: Linux
Classifier: Environment :: MacOS X
Classifier: Topic :: Internet
Requires-Python: >=3.7
Requires-Dist: libsass (>=0.20.0)
Requires-Dist: httpx (>=0.12.1)
Requires-Dist: pydantic (>=1.5)
Requires-Dist: PyYAML (>=5.3.1)
Requires-Dist: typer (>=0.1.0)
Requires-Dist: watchgod (>=0.6)
